logicplum/__init__.py
logicplum/aicloud/__init__.py
logicplum/aicloud/config.py
logicplum/aicloud/modeling/__init__.py
logicplum/aicloud/modeling/training.py
logicplum/aicloud/monitoring/__init__.py
logicplum/aicloud/monitoring/model_monitoring.py
logicplum/aicloud/plots/__init__.py
logicplum/aicloud/plots/graph_plots.py
logicplum/aicloud/prediction/__init__.py
logicplum/aicloud/prediction/get_prediction.py
logicplum/aicloud/reports/__init__.py
logicplum/aicloud/reports/get_report.py
logicplum/aicloud/status/__init__.py
logicplum/aicloud/status/get_status.py
logicplum/aicloud/users/__init__.py
logicplum/aicloud/users/client.py
logicplum_ai-1.3.9.dist-info/METADATA
logicplum_ai-1.3.9.dist-info/WHEEL
logicplum_ai-1.3.9.dist-info/top_level.txt
logicplum_ai-1.3.9.dist-info/RECORD
