Metadata-Version: 2.1
Name: logicplum-ai
Version: 1.3.9
Requires-Dist: requests
Requires-Dist: Pillow
